[
  {
    "timestamp": "2025-11-30T01:56:24.690Z",
    "channelId": "UC5SEjVYIq_ITTbUUPVLOZMQ",
    "subscribers": 96,
    "viewCount": 14931,
    "videoCount": 24,
    "name": "ΞLΞMΞNТ   II5",
    "avatar": "https://yt3.ggpht.com/3CcJPVkhO0yhtNL7DTgnG1gARnMWp0ryT0RcmtbYpF9qqYA0y6BmbZDBiN18aW2YRvdoFxEy7DY=s200-c-k-c0x00ffffff-no-rj"
  },
  {
    "timestamp": "2025-11-30T11:35:13.548Z",
    "channelId": "UC5SEjVYIq_ITTbUUPVLOZMQ",
    "subscribers": 96,
    "viewCount": 14931,
    "videoCount": 24,
    "name": "ΞLΞMΞNТ   II5",
    "avatar": "https://yt3.ggpht.com/3CcJPVkhO0yhtNL7DTgnG1gARnMWp0ryT0RcmtbYpF9qqYA0y6BmbZDBiN18aW2YRvdoFxEy7DY=s200-c-k-c0x00ffffff-no-rj"
  }
]