[
  {
    "timestamp": "2025-11-30T01:54:37.448Z",
    "channelId": "UCsJj-x52HymlR1OBDekdY6g",
    "subscribers": 109010,
    "viewCount": 7295389,
    "videoCount": 338,
    "name": "Rabail rk ",
    "avatar": "https://yt3.ggpht.com/K8FJhuPHnL14_AIRMX9W00tQ5PDdp98wis23Qig60DUe5J7OYHVJqGx9S41JEI24ebL3EnMfmb0=s200-c-k-c0x00ffffff-no-rj"
  },
  {
    "timestamp": "2025-11-30T11:32:12.960Z",
    "channelId": "UCsJj-x52HymlR1OBDekdY6g",
    "subscribers": 109011,
    "viewCount": 7295615,
    "videoCount": 338,
    "name": "Rabail rk ",
    "avatar": "https://yt3.ggpht.com/K8FJhuPHnL14_AIRMX9W00tQ5PDdp98wis23Qig60DUe5J7OYHVJqGx9S41JEI24ebL3EnMfmb0=s200-c-k-c0x00ffffff-no-rj"
  },
  {
    "timestamp": "2025-11-30T11:33:14.604Z",
    "channelId": "UCsJj-x52HymlR1OBDekdY6g",
    "subscribers": 109023,
    "viewCount": 7298629,
    "videoCount": 338,
    "name": "Rabail rk ",
    "avatar": "https://yt3.ggpht.com/K8FJhuPHnL14_AIRMX9W00tQ5PDdp98wis23Qig60DUe5J7OYHVJqGx9S41JEI24ebL3EnMfmb0=s200-c-k-c0x00ffffff-no-rj"
  },
  {
    "timestamp": "2025-11-30T13:02:34.996Z",
    "channelId": "UCsJj-x52HymlR1OBDekdY6g",
    "subscribers": 109024,
    "viewCount": 7298362,
    "videoCount": 338,
    "name": "Rabail rk ",
    "avatar": "https://yt3.ggpht.com/K8FJhuPHnL14_AIRMX9W00tQ5PDdp98wis23Qig60DUe5J7OYHVJqGx9S41JEI24ebL3EnMfmb0=s200-c-k-c0x00ffffff-no-rj"
  }
]