[
  {
    "timestamp": "2025-11-30T01:54:49.498Z",
    "channelId": "UCx_m0F8uyjAA5N4dw-zhugA",
    "subscribers": 3310663,
    "viewCount": 2079242465,
    "videoCount": 323,
    "name": "Comptines d'Afrique",
    "avatar": "https://yt3.ggpht.com/ytc/AIdro_nSRuTgqlWS1_eyHbzl2LZmKqfAv6JoarkhTmuRfI-W0g=s200-c-k-c0x00ffffff-no-rj"
  },
  {
    "timestamp": "2025-11-30T11:32:37.289Z",
    "channelId": "UCx_m0F8uyjAA5N4dw-zhugA",
    "subscribers": 3311402,
    "viewCount": 2080614705,
    "videoCount": 323,
    "name": "Comptines d'Afrique",
    "avatar": "https://yt3.ggpht.com/ytc/AIdro_nSRuTgqlWS1_eyHbzl2LZmKqfAv6JoarkhTmuRfI-W0g=s200-c-k-c0x00ffffff-no-rj"
  },
  {
    "timestamp": "2025-11-30T11:33:30.221Z",
    "channelId": "UCx_m0F8uyjAA5N4dw-zhugA",
    "subscribers": 3311425,
    "viewCount": 2080652243,
    "videoCount": 323,
    "name": "Comptines d'Afrique",
    "avatar": "https://yt3.ggpht.com/ytc/AIdro_nSRuTgqlWS1_eyHbzl2LZmKqfAv6JoarkhTmuRfI-W0g=s200-c-k-c0x00ffffff-no-rj"
  },
  {
    "timestamp": "2025-11-30T13:02:44.733Z",
    "channelId": "UCx_m0F8uyjAA5N4dw-zhugA",
    "subscribers": 3311453,
    "viewCount": 2080697357,
    "videoCount": 323,
    "name": "Comptines d'Afrique",
    "avatar": "https://yt3.ggpht.com/ytc/AIdro_nSRuTgqlWS1_eyHbzl2LZmKqfAv6JoarkhTmuRfI-W0g=s200-c-k-c0x00ffffff-no-rj"
  }
]