[
  {
    "timestamp": "2025-11-30T01:54:54.349Z",
    "channelId": "UCBJZjd0P9zhNlgBOHrKUn7g",
    "subscribers": 1860,
    "viewCount": 764273,
    "videoCount": 414,
    "name": "D-Kuppler",
    "avatar": "https://yt3.ggpht.com/6PSwapR9thC_k_iR4COpoEzKhESjGx5VcdFThgFFMMoTa5Ajwx9-pPlQrP6Zc_vt5JP_TlgB=s200-c-k-c0x00ffffff-no-rj"
  },
  {
    "timestamp": "2025-11-30T11:32:47.237Z",
    "channelId": "UCBJZjd0P9zhNlgBOHrKUn7g",
    "subscribers": 1860,
    "viewCount": 764918,
    "videoCount": 414,
    "name": "D-Kuppler",
    "avatar": "https://yt3.ggpht.com/6PSwapR9thC_k_iR4COpoEzKhESjGx5VcdFThgFFMMoTa5Ajwx9-pPlQrP6Zc_vt5JP_TlgB=s200-c-k-c0x00ffffff-no-rj"
  },
  {
    "timestamp": "2025-11-30T11:33:36.647Z",
    "channelId": "UCBJZjd0P9zhNlgBOHrKUn7g",
    "subscribers": 1860,
    "viewCount": 764929,
    "videoCount": 414,
    "name": "D-Kuppler",
    "avatar": "https://yt3.ggpht.com/6PSwapR9thC_k_iR4COpoEzKhESjGx5VcdFThgFFMMoTa5Ajwx9-pPlQrP6Zc_vt5JP_TlgB=s200-c-k-c0x00ffffff-no-rj"
  },
  {
    "timestamp": "2025-11-30T13:02:48.998Z",
    "channelId": "UCBJZjd0P9zhNlgBOHrKUn7g",
    "subscribers": 1860,
    "viewCount": 764943,
    "videoCount": 414,
    "name": "D-Kuppler",
    "avatar": "https://yt3.ggpht.com/6PSwapR9thC_k_iR4COpoEzKhESjGx5VcdFThgFFMMoTa5Ajwx9-pPlQrP6Zc_vt5JP_TlgB=s200-c-k-c0x00ffffff-no-rj"
  }
]