[
  {
    "timestamp": "2025-11-30T01:54:37.719Z",
    "channelId": "UC-8TG2HoLIehbIab3ea6seg",
    "subscribers": 107192,
    "viewCount": 204249183,
    "videoCount": 358,
    "name": "RK - Topic",
    "avatar": "https://yt3.ggpht.com/40vItcy4YLchffjvdIte7lwrbN7CgzlV6Ch-5QcYmC-JFNCuhlmVI_ojEfPHcwP67LbL1JiAWMk=s200-c-k-c0x00ffffff-no-rj"
  },
  {
    "timestamp": "2025-11-30T11:32:13.509Z",
    "channelId": "UC-8TG2HoLIehbIab3ea6seg",
    "subscribers": 107192,
    "viewCount": 204252678,
    "videoCount": 358,
    "name": "RK - Topic",
    "avatar": "https://yt3.ggpht.com/40vItcy4YLchffjvdIte7lwrbN7CgzlV6Ch-5QcYmC-JFNCuhlmVI_ojEfPHcwP67LbL1JiAWMk=s200-c-k-c0x00ffffff-no-rj"
  },
  {
    "timestamp": "2025-11-30T11:33:14.942Z",
    "channelId": "UC-8TG2HoLIehbIab3ea6seg",
    "subscribers": 107192,
    "viewCount": 204305001,
    "videoCount": 358,
    "name": "RK - Topic",
    "avatar": "https://yt3.ggpht.com/40vItcy4YLchffjvdIte7lwrbN7CgzlV6Ch-5QcYmC-JFNCuhlmVI_ojEfPHcwP67LbL1JiAWMk=s200-c-k-c0x00ffffff-no-rj"
  },
  {
    "timestamp": "2025-11-30T13:02:36.087Z",
    "channelId": "UC-8TG2HoLIehbIab3ea6seg",
    "subscribers": 107192,
    "viewCount": 204299481,
    "videoCount": 358,
    "name": "RK - Topic",
    "avatar": "https://yt3.ggpht.com/40vItcy4YLchffjvdIte7lwrbN7CgzlV6Ch-5QcYmC-JFNCuhlmVI_ojEfPHcwP67LbL1JiAWMk=s200-c-k-c0x00ffffff-no-rj"
  }
]