[
  {
    "timestamp": "2025-11-30T01:56:46.671Z",
    "channelId": "UCFnUXxr10OjMsunn69x-Q4A",
    "subscribers": 0,
    "viewCount": 7,
    "videoCount": 1,
    "name": " 🗡️НОЖ 🗡️",
    "avatar": "https://yt3.ggpht.com/vr4ciEFmF9otzRGnYFFhebG8_vfxCaMpVIA-bl4tBbuf4bTEeEjYdLnECkih8Oty-LbQ2Gvn=s200-c-k-c0x00ffffff-no-rj"
  },
  {
    "timestamp": "2025-11-30T11:35:36.623Z",
    "channelId": "UCFnUXxr10OjMsunn69x-Q4A",
    "subscribers": 0,
    "viewCount": 7,
    "videoCount": 1,
    "name": " 🗡️НОЖ 🗡️",
    "avatar": "https://yt3.ggpht.com/vr4ciEFmF9otzRGnYFFhebG8_vfxCaMpVIA-bl4tBbuf4bTEeEjYdLnECkih8Oty-LbQ2Gvn=s200-c-k-c0x00ffffff-no-rj"
  }
]