[
  {
    "timestamp": "2025-11-30T01:55:07.598Z",
    "channelId": "UCM5AZGYhhHcpNZyVaMSpHUg",
    "subscribers": 0,
    "viewCount": 52,
    "videoCount": 11,
    "name": "LUCKY NUMBER FIVE - Topic",
    "avatar": "https://yt3.ggpht.com/nOM76Di__JtKmo2aCmtJzUAgwZxRjsTjePB-YwF5ttfLMy1Ee3wWdNoqdmcRdUd5iSGbSas4Ng=s200-c-k-c0x00ffffff-no-rj"
  },
  {
    "timestamp": "2025-11-30T11:33:53.532Z",
    "channelId": "UCM5AZGYhhHcpNZyVaMSpHUg",
    "subscribers": 0,
    "viewCount": 52,
    "videoCount": 11,
    "name": "LUCKY NUMBER FIVE - Topic",
    "avatar": "https://yt3.ggpht.com/nOM76Di__JtKmo2aCmtJzUAgwZxRjsTjePB-YwF5ttfLMy1Ee3wWdNoqdmcRdUd5iSGbSas4Ng=s200-c-k-c0x00ffffff-no-rj"
  }
]